pytestutils/__init__.py
pytestutils/mock_import.py
pytestutils-0.1.dist-info/DESCRIPTION.rst
pytestutils-0.1.dist-info/METADATA
pytestutils-0.1.dist-info/RECORD
pytestutils-0.1.dist-info/WHEEL
pytestutils-0.1.dist-info/metadata.json
pytestutils-0.1.dist-info/pbr.json
pytestutils-0.1.dist-info/top_level.txt
